gensite/__init__.py
gensite-0.1.0.dist-info/LICENSE
gensite-0.1.0.dist-info/METADATA
gensite-0.1.0.dist-info/WHEEL
gensite-0.1.0.dist-info/top_level.txt
gensite-0.1.0.dist-info/RECORD
